{"name":"I remove the item in my shopping cart","id":"change-item-s-quantity-on-my-shopping-cart;i-remove-the-item-in-my-shopping-cart","testSteps":[{"number":1,"description":"Given I am on product page","duration":10628,"startTime":"2022-05-18T15:53:13.411178+07:00[Asia/Jakarta]","screenshots":[{"screenshot":"80af40d6e0ddd814b903a7eeafe654dc42caf4f09f388809c4609494672bdf6e.png","timeStamp":1652864004039}],"result":"SUCCESS","precondition":false,"level":0,"children":[{"number":2,"description":"Open url","duration":7041,"startTime":"2022-05-18T15:53:13.456188300+07:00[Asia/Jakarta]","screenshots":[{"screenshot":"49a3ec3fe6e588bb357024d38ea075b8250cb5f32bd132770e4d40bc98d606c0.png","timeStamp":1652864000497}],"result":"SUCCESS","precondition":false,"level":1},{"number":3,"description":"Input email: inggrit@gmail.com","duration":791,"startTime":"2022-05-18T15:53:20.499633200+07:00[Asia/Jakarta]","screenshots":[{"screenshot":"49a3ec3fe6e588bb357024d38ea075b8250cb5f32bd132770e4d40bc98d606c0.png","timeStamp":1652864000507},{"screenshot":"d1ff4dca613d064b5b0d6931593e700b96467e10aa3130f0f4c794c281cbb3d3.png","timeStamp":1652864001291}],"result":"SUCCESS","precondition":false,"level":1},{"number":4,"description":"Input password: Passwordtest321","duration":739,"startTime":"2022-05-18T15:53:21.296528400+07:00[Asia/Jakarta]","screenshots":[{"screenshot":"d1ff4dca613d064b5b0d6931593e700b96467e10aa3130f0f4c794c281cbb3d3.png","timeStamp":1652864001305},{"screenshot":"a45555a2ae2e4dbcdcb167f3b0c531c6354ff771bac28ff38188c446695307f8.png","timeStamp":1652864002036}],"result":"SUCCESS","precondition":false,"level":1},{"number":5,"description":"Click login button","duration":1985,"startTime":"2022-05-18T15:53:22.044149100+07:00[Asia/Jakarta]","screenshots":[{"screenshot":"9f7e4f9f2516bb9a030811cc3fd9870f55a5f22cab438662743f946f6e528cbe.png","timeStamp":1652864002509},{"screenshot":"80af40d6e0ddd814b903a7eeafe654dc42caf4f09f388809c4609494672bdf6e.png","timeStamp":1652864004029}],"result":"SUCCESS","precondition":false,"level":1}]},{"number":6,"description":"When I click buy first product button on product page","duration":12297,"startTime":"2022-05-18T15:53:24.044543700+07:00[Asia/Jakarta]","screenshots":[{"screenshot":"09c17d0ca97282def230c9d509ce33d7b58adf9a8ec8a3a0ce8a5c60a536d6fe.png","timeStamp":1652864016342}],"result":"SUCCESS","precondition":false,"level":0,"children":[{"number":7,"description":"Click first product","duration":11868,"startTime":"2022-05-18T15:53:24.462175600+07:00[Asia/Jakarta]","screenshots":[{"screenshot":"f5d72973b97ffb2b9c347bdaea51478810f802fd0d879d56737cfedc58dd7510.png","timeStamp":1652864015703},{"screenshot":"09c17d0ca97282def230c9d509ce33d7b58adf9a8ec8a3a0ce8a5c60a536d6fe.png","timeStamp":1652864016330}],"result":"SUCCESS","precondition":false,"level":1}]},{"number":8,"description":"And I click shopping cart button","duration":1120,"startTime":"2022-05-18T15:53:36.346154200+07:00[Asia/Jakarta]","screenshots":[{"screenshot":"988fa1d3c2080e17a21529ce9e5cf9be1c49055403865650ad3d1aa7b92d4d72.png","timeStamp":1652864017466}],"result":"SUCCESS","precondition":false,"level":0,"children":[{"number":9,"description":"Click shopping cart","duration":1098,"startTime":"2022-05-18T15:53:36.359159300+07:00[Asia/Jakarta]","screenshots":[{"screenshot":"988fa1d3c2080e17a21529ce9e5cf9be1c49055403865650ad3d1aa7b92d4d72.png","timeStamp":1652864017457}],"result":"SUCCESS","precondition":false,"level":1}]},{"number":10,"description":"And I click - sign on the product","duration":649,"startTime":"2022-05-18T15:53:37.471432100+07:00[Asia/Jakarta]","screenshots":[{"screenshot":"076875ed388d7ba8b3eeb2dea3920cb712b12b5faea1c4adba34bc15846b0ee5.png","timeStamp":1652864018120}],"result":"SUCCESS","precondition":false,"level":0,"children":[{"number":11,"description":"Click reduce button","duration":630,"startTime":"2022-05-18T15:53:37.480438500+07:00[Asia/Jakarta]","screenshots":[{"screenshot":"076875ed388d7ba8b3eeb2dea3920cb712b12b5faea1c4adba34bc15846b0ee5.png","timeStamp":1652864018110}],"result":"SUCCESS","precondition":false,"level":1}]},{"number":12,"description":"Then I validate the product is removed","duration":330,"startTime":"2022-05-18T15:53:38.122733600+07:00[Asia/Jakarta]","screenshots":[{"screenshot":"d0d3598a25adfc627cf8abd2ef78679da4436be5b4c9b8b4cbf96352734f30ea.png","timeStamp":1652864018452}],"result":"SUCCESS","precondition":false,"level":0,"children":[{"number":13,"description":"Verify cart is empty","duration":314,"startTime":"2022-05-18T15:53:38.131738800+07:00[Asia/Jakarta]","screenshots":[{"screenshot":"d0d3598a25adfc627cf8abd2ef78679da4436be5b4c9b8b4cbf96352734f30ea.png","timeStamp":1652864018445}],"result":"SUCCESS","precondition":false,"level":1}]}],"userStory":{"id":"change-item-s-quantity-on-my-shopping-cart","storyName":"Change item\u0027s quantity on my shopping cart","displayName":"Change item\u0027s quantity on my shopping cart","path":"Order.feature","narrative":"  As a user\n  I should be able to change the quantity of the item on my shopping cart\n  So that i can do transaction","type":"feature"},"featureTag":{"name":"Change item\u0027s quantity on my shopping cart","type":"feature","displayName":"Change item\u0027s quantity on my shopping cart"},"title":"I remove the item in my shopping cart","description":"","tags":[{"name":"Change item\u0027s quantity on my shopping cart","type":"feature","displayName":"Change item\u0027s quantity on my shopping cart"}],"startTime":"2022-05-18T15:53:13.399181400+07:00[Asia/Jakarta]","duration":25057,"projectKey":"","sessionId":"468fb91f9e87f10d77a05c2573fcc935","driver":"chrome","isManualTestingUpToDate":false,"manual":false,"testSource":"Cucumber","result":"SUCCESS"}